nonebot_plugin_animeres/__init__.py
nonebot_plugin_animeres/config.py
nonebot_plugin_animeres/internal.py
nonebot_plugin_animeres/resources/__init__.py
nonebot_plugin_animeres/resources/anoneko.py
nonebot_plugin_animeres/resources/dongmanhuayuan.py
nonebot_plugin_animeres/resources/myheartsite.py
nonebot_plugin_animeres/schemas.py
nonebot_plugin_animeres/utils.py
nonebot_plugin_animeres-1.0.4.dist-info/LICENSE
nonebot_plugin_animeres-1.0.4.dist-info/METADATA
nonebot_plugin_animeres-1.0.4.dist-info/WHEEL
nonebot_plugin_animeres-1.0.4.dist-info/RECORD
