Metadata-Version: 2.1
Name: nonebot-plugin-animeres
Version: 1.0.4
Summary: 动漫资源获取插件
License: GPL-2.0
Keywords: nonebot,nonebot2,animeres,anime
Author: MelodyKnit
Author-email: 2711402357@qq.com
Requires-Python: >=3.8,<4.0
Classifier: License :: OSI Approved :: GNU General Public License v2 (GPLv2)
Classifier: Programming Language :: Python :: 3
Classifier: Programming Language :: Python :: 3.8
Classifier: Programming Language :: Python :: 3.9
Classifier: Programming Language :: Python :: 3.10
Classifier: Programming Language :: Python :: 3.11
Requires-Dist: fake-useragent (>=1.1.3,<2.0.0)
Requires-Dist: httpx (>=0.20.0,<1.0.0)
Requires-Dist: lxml (>=4.9.2,<5.0.0)
Requires-Dist: nonebot-adapter-onebot (>=2.2.3,<3.0.0)
Requires-Dist: nonebot2 (>=2.0.0rc1,<3.0.0)
